yagamee/__init__.py
yagamee/dataframe_tools.py
yagamee/formats.py
yagamee/matplotlib_tools.py
yagamee/yagamee_rcparams.py
yagamee-0.2.3.dist-info/LICENSE
yagamee-0.2.3.dist-info/METADATA
yagamee-0.2.3.dist-info/WHEEL
yagamee-0.2.3.dist-info/top_level.txt
yagamee-0.2.3.dist-info/RECORD
