Metadata-Version: 2.1
Name: yagamee
Version: 0.2.3
Summary: 理系大学生のためのレポート作成支援ツール
Home-page: https://github.com/Mya-Mya/yagamee
Author: Mya-Mya
Author-email: 
License: MIT
Keywords: matplotlib,graphing,report,report-making,university,science
Classifier: Programming Language :: Python :: 3.5
Classifier: Programming Language :: Python :: 3.6
Classifier: Programming Language :: Python :: 3.7
License-File: LICENSE
Requires-Dist: matplotlib
Requires-Dist: japanize-matplotlib
Requires-Dist: pandas
Requires-Dist: sigfig
